{
	"animations": [
		{
			"offsets": [
				0,
				0
			],
			"loop": false,
			"fps": 24,
			"anim": "idle",
			"indices": [],
			"name": "Mario Idle"
		},
		{
			"offsets": [
				40,
				0
			],
			"loop": false,
			"fps": 24,
			"anim": "singLEFT",
			"indices": [],
			"name": "Mario Left"
		},
		{
			"offsets": [
				0,
				0
			],
			"loop": false,
			"fps": 24,
			"anim": "singDOWN",
			"indices": [],
			"name": "Mario Down"
		},
		{
			"offsets": [
				0,
				20
			],
			"loop": false,
			"fps": 24,
			"anim": "singUP",
			"indices": [],
			"name": "Mario Up"
		},
		{
			"offsets": [
				-20,
				10
			],
			"loop": false,
			"fps": 24,
			"anim": "singRIGHT",
			"indices": [],
			"name": "Mario Right"
		}
	],
	"no_antialiasing": true,
	"image": "characters/Mario",
	"position": [
		258,
		521
	],
	"healthicon": "mario-nes",
	"flip_x": false,
	"healthbar_colors": [
		181,
		49,
		32
	],
	"camera_position": [
		-250,
		-210
	],
	"sing_duration": 6.1,
	"scale": 10
}